ephysvibe/__init__.py
ephysvibe/_version.py
ephysvibe/pipelines/__init__.py
ephysvibe/pipelines/sp_sorting.py
ephysvibe/pipelines/split_areas.py
ephysvibe/spike_sorting/__init__.py
ephysvibe/spike_sorting/config.py
ephysvibe/spike_sorting/data_structure.py
ephysvibe/spike_sorting/pre_treat_oe.py
ephysvibe/spike_sorting/utils_oe.py
ephysvibe/trials/__init__.py
ephysvibe/trials/select_trials.py
ephysvibe/trials/spikes/__init__.py
ephysvibe/trials/spikes/firing_rate.py
ephysvibe-0.0.2.dist-info/METADATA
ephysvibe-0.0.2.dist-info/WHEEL
ephysvibe-0.0.2.dist-info/top_level.txt
ephysvibe-0.0.2.dist-info/RECORD
