Metadata-Version: 2.1
Name: ephysvibe
Version: 0.0.2
Summary: .
Home-page: https://github.com/camilosada/EphysVibe
Download-URL: https://github.com/camilosada/EphysVibe
Maintainer: Camila Losada
Maintainer-email: camilaalosada@gmail.com
Project-URL: Source, https://github.com/camilosada/EphysVibe
Project-URL: Tracker, https://github.com/camilosada/EphysVibe/issues/
Keywords: electrophysiology neuroscience
Platform: any
Classifier: Intended Audience :: Science/Research
Classifier: Intended Audience :: Developers
Classifier: License :: OSI Approved :: BSD License
Classifier: Programming Language :: Python
Classifier: Topic :: Software Development
Classifier: Topic :: Scientific/Engineering
Classifier: Topic :: Scientific/Engineering :: Human Machine Interfaces
Classifier: Operating System :: Microsoft :: Windows
Classifier: Operating System :: POSIX
Classifier: Operating System :: Unix
Classifier: Operating System :: MacOS
Classifier: Programming Language :: Python :: 3
Requires-Python: >=3.7
Requires-Dist: fooof (>=1.0.0)
Requires-Dist: matplotlib (>=3.6.2)
Requires-Dist: mne (>=1.2.3)
Requires-Dist: numpy (>=1.23.4)
Requires-Dist: open-ephys-python-tools (>=0.1.2)
Requires-Dist: pandas (>=1.5.1)
Requires-Dist: scipy (>=1.9.3)
Requires-Dist: seaborn (>=0.12.1)
